FacebookMessengerAnalyzer/FacebookMessengerAnalyzer.py
FacebookMessengerAnalyzer/__init__.py
FacebookMessengerAnalyzer-0.0.3.dist-info/LICENSE.txt
FacebookMessengerAnalyzer-0.0.3.dist-info/METADATA
FacebookMessengerAnalyzer-0.0.3.dist-info/WHEEL
FacebookMessengerAnalyzer-0.0.3.dist-info/top_level.txt
FacebookMessengerAnalyzer-0.0.3.dist-info/RECORD
