Metadata-Version: 2.1
Name: FacebookMessengerAnalyzer
Version: 0.0.3
Summary: A library which allows users to easily run simple Data Analytics on their Facebook Messenger Data
Home-page: https://github.com/zegarmm001/FacebookMessengerAnalyzer
Author: Marcin Zegarmistrz
License: UNKNOWN
Platform: UNKNOWN
Classifier: Programming Language :: Python :: 3
Classifier: License :: OSI Approved :: MIT License
Classifier: Operating System :: OS Independent
Requires-Python: >=3.6
Requires-Dist: pandas
Requires-Dist: nltk
Requires-Dist: numpy
Requires-Dist: matplotlib
Requires-Dist: tabulate
